<?xml version="1.0" encoding="utf-8"?>
<map>
  <mapsize>
    <mapx>24</mapx>
    <mapy>10</mapy>
  </mapsize>
  <tileset x="0" y="0">
    <tilex>-1</tilex>
    <tiley>-1</tiley>
    <perms>Impassable</perms>
  </tileset>
  <tileset x="1" y="0">
    <tilex>8</tilex>
    <tiley>0</tiley>
    <perms>Open</perms>
  </tileset>
  <tileset x="2" y="0">
    <tilex>0</tilex>
    <tiley>0</tiley>
    <perms>Open</perms>
  </tileset>
  <tileset x="3" y="0">
    <tilex>0</tilex>
    <tiley>0</tiley>
    <perms>Open</perms>
  </tileset>
  <tileset x="4" y="0">
    <tilex>0</tilex>
    <tiley>0</tiley>
    <perms>Open</perms>
  </tileset>
  <tileset x="5" y="0">
    <tilex>0</tilex>
    <tiley>0</tiley>
    <perms>Open</perms>
  </tileset>
  <tileset x="6" y="0">
    <tilex>0</tilex>
    <tiley>0</tiley>
    <perms>Open</perms>
  </tileset>
  <tileset x="7" y="0">
    <tilex>0</tilex>
    <tiley>0</tiley>
    <perms>Open</perms>
  </tileset>
  <tileset x="8" y="0">
    <tilex>1</tilex>
    <tiley>0</tiley>
    <perms>Open</perms>
  </tileset>
  <tileset x="9" y="0">
    <tilex>0</tilex>
    <tiley>0</tiley>
    <perms>Open</perms>
  </tileset>
  <tileset x="10" y="0">
    <tilex>0</tilex>
    <tiley>0</tiley>
    <perms>Open</perms>
  </tileset>
  <tileset x="11" y="0">
    <tilex>0</tilex>
    <tiley>0</tiley>
    <perms>Open</perms>
  </tileset>
  <tileset x="12" y="0">
    <tilex>0</tilex>
    <tiley>0</tiley>
    <perms>Open</perms>
  </tileset>
  <tileset x="13" y="0">
    <tilex>0</tilex>
    <tiley>0</tiley>
    <perms>Open</perms>
  </tileset>
  <tileset x="14" y="0">
    <tilex>0</tilex>
    <tiley>0</tiley>
    <perms>Open</perms>
  </tileset>
  <tileset x="15" y="0">
    <tilex>0</tilex>
    <tiley>0</tiley>
    <perms>Open</perms>
  </tileset>
  <tileset x="16" y="0">
    <tilex>0</tilex>
    <tiley>0</tiley>
    <perms>Open</perms>
  </tileset>
  <tileset x="17" y="0">
    <tilex>0</tilex>
    <tiley>0</tiley>
    <perms>Open</perms>
  </tileset>
  <tileset x="18" y="0">
    <tilex>0</tilex>
    <tiley>0</tiley>
    <perms>Open</perms>
  </tileset>
  <tileset x="19" y="0">
    <tilex>0</tilex>
    <tiley>0</tiley>
    <perms>Open</perms>
  </tileset>
  <tileset x="20" y="0">
    <tilex>0</tilex>
    <tiley>0</tiley>
    <perms>Open</perms>
  </tileset>
  <tileset x="21" y="0">
    <tilex>0</tilex>
    <tiley>0</tiley>
    <perms>Open</perms>
  </tileset>
  <tileset x="22" y="0">
    <tilex>0</tilex>
    <tiley>0</tiley>
    <perms>Open</perms>
  </tileset>
  <tileset x="23" y="0">
    <tilex>-1</tilex>
    <tiley>-1</tiley>
    <perms>Impassable</perms>
  </tileset>
  <tileset x="0" y="1">
    <tilex>-1</tilex>
    <tiley>-1</tiley>
    <perms>Impassable</perms>
  </tileset>
  <tileset x="1" y="1">
    <tilex>0</tilex>
    <tiley>0</tiley>
    <perms>Open</perms>
  </tileset>
  <tileset x="2" y="1">
    <tilex>0</tilex>
    <tiley>0</tiley>
    <perms>Open</perms>
  </tileset>
  <tileset x="3" y="1">
    <tilex>0</tilex>
    <tiley>0</tiley>
    <perms>Open</perms>
  </tileset>
  <tileset x="4" y="1">
    <tilex>0</tilex>
    <tiley>0</tiley>
    <perms>Open</perms>
  </tileset>
  <tileset x="5" y="1">
    <tilex>0</tilex>
    <tiley>0</tiley>
    <perms>Open</perms>
  </tileset>
  <tileset x="6" y="1">
    <tilex>0</tilex>
    <tiley>0</tiley>
    <perms>Open</perms>
  </tileset>
  <tileset x="7" y="1">
    <tilex>0</tilex>
    <tiley>0</tiley>
    <perms>Open</perms>
  </tileset>
  <tileset x="8" y="1">
    <tilex>0</tilex>
    <tiley>0</tiley>
    <perms>Open</perms>
  </tileset>
  <tileset x="9" y="1">
    <tilex>0</tilex>
    <tiley>0</tiley>
    <perms>Open</perms>
  </tileset>
  <tileset x="10" y="1">
    <tilex>0</tilex>
    <tiley>0</tiley>
    <perms>Open</perms>
  </tileset>
  <tileset x="11" y="1">
    <tilex>0</tilex>
    <tiley>0</tiley>
    <perms>Open</perms>
  </tileset>
  <tileset x="12" y="1">
    <tilex>0</tilex>
    <tiley>0</tiley>
    <perms>Open</perms>
  </tileset>
  <tileset x="13" y="1">
    <tilex>0</tilex>
    <tiley>0</tiley>
    <perms>Open</perms>
  </tileset>
  <tileset x="14" y="1">
    <tilex>0</tilex>
    <tiley>0</tiley>
    <perms>Open</perms>
  </tileset>
  <tileset x="15" y="1">
    <tilex>0</tilex>
    <tiley>0</tiley>
    <perms>Open</perms>
  </tileset>
  <tileset x="16" y="1">
    <tilex>0</tilex>
    <tiley>0</tiley>
    <perms>Open</perms>
  </tileset>
  <tileset x="17" y="1">
    <tilex>0</tilex>
    <tiley>0</tiley>
    <perms>Open</perms>
  </tileset>
  <tileset x="18" y="1">
    <tilex>0</tilex>
    <tiley>0</tiley>
    <perms>Open</perms>
  </tileset>
  <tileset x="19" y="1">
    <tilex>0</tilex>
    <tiley>0</tiley>
    <perms>Open</perms>
  </tileset>
  <tileset x="20" y="1">
    <tilex>0</tilex>
    <tiley>0</tiley>
    <perms>Open</perms>
  </tileset>
  <tileset x="21" y="1">
    <tilex>0</tilex>
    <tiley>0</tiley>
    <perms>Open</perms>
  </tileset>
  <tileset x="22" y="1">
    <tilex>0</tilex>
    <tiley>0</tiley>
    <perms>Open</perms>
  </tileset>
  <tileset x="23" y="1">
    <tilex>-1</tilex>
    <tiley>-1</tiley>
    <perms>Impassable</perms>
  </tileset>
  <tileset x="0" y="2">
    <tilex>0</tilex>
    <tiley>0</tiley>
    <perms>Open</perms>
  </tileset>
  <tileset x="1" y="2">
    <tilex>0</tilex>
    <tiley>0</tiley>
    <perms>Open</perms>
  </tileset>
  <tileset x="2" y="2">
    <tilex>0</tilex>
    <tiley>0</tiley>
    <perms>Open</perms>
  </tileset>
  <tileset x="3" y="2">
    <tilex>0</tilex>
    <tiley>0</tiley>
    <perms>Open</perms>
  </tileset>
  <tileset x="4" y="2">
    <tilex>0</tilex>
    <tiley>0</tiley>
    <perms>Open</perms>
  </tileset>
  <tileset x="5" y="2">
    <tilex>0</tilex>
    <tiley>0</tiley>
    <perms>Open</perms>
  </tileset>
  <tileset x="6" y="2">
    <tilex>0</tilex>
    <tiley>0</tiley>
    <perms>Open</perms>
  </tileset>
  <tileset x="7" y="2">
    <tilex>0</tilex>
    <tiley>0</tiley>
    <perms>Open</perms>
  </tileset>
  <tileset x="8" y="2">
    <tilex>0</tilex>
    <tiley>0</tiley>
    <perms>Open</perms>
  </tileset>
  <tileset x="9" y="2">
    <tilex>0</tilex>
    <tiley>0</tiley>
    <perms>Open</perms>
  </tileset>
  <tileset x="10" y="2">
    <tilex>0</tilex>
    <tiley>0</tiley>
    <perms>Open</perms>
  </tileset>
  <tileset x="11" y="2">
    <tilex>1</tilex>
    <tiley>0</tiley>
    <perms>Open</perms>
  </tileset>
  <tileset x="12" y="2">
    <tilex>0</tilex>
    <tiley>0</tiley>
    <perms>Open</perms>
  </tileset>
  <tileset x="13" y="2">
    <tilex>0</tilex>
    <tiley>0</tiley>
    <perms>Open</perms>
  </tileset>
  <tileset x="14" y="2">
    <tilex>0</tilex>
    <tiley>0</tiley>
    <perms>Open</perms>
  </tileset>
  <tileset x="15" y="2">
    <tilex>0</tilex>
    <tiley>0</tiley>
    <perms>Open</perms>
  </tileset>
  <tileset x="16" y="2">
    <tilex>0</tilex>
    <tiley>0</tiley>
    <perms>Open</perms>
  </tileset>
  <tileset x="17" y="2">
    <tilex>0</tilex>
    <tiley>0</tiley>
    <perms>Open</perms>
  </tileset>
  <tileset x="18" y="2">
    <tilex>0</tilex>
    <tiley>0</tiley>
    <perms>Open</perms>
  </tileset>
  <tileset x="19" y="2">
    <tilex>0</tilex>
    <tiley>0</tiley>
    <perms>Open</perms>
  </tileset>
  <tileset x="20" y="2">
    <tilex>0</tilex>
    <tiley>0</tiley>
    <perms>Open</perms>
  </tileset>
  <tileset x="21" y="2">
    <tilex>0</tilex>
    <tiley>0</tiley>
    <perms>Open</perms>
  </tileset>
  <tileset x="22" y="2">
    <tilex>0</tilex>
    <tiley>0</tiley>
    <perms>Open</perms>
  </tileset>
  <tileset x="23" y="2">
    <tilex>-1</tilex>
    <tiley>-1</tiley>
    <perms>Impassable</perms>
  </tileset>
  <tileset x="0" y="3">
    <tilex>-1</tilex>
    <tiley>-1</tiley>
    <perms>Impassable</perms>
  </tileset>
  <tileset x="1" y="3">
    <tilex>0</tilex>
    <tiley>0</tiley>
    <perms>Open</perms>
  </tileset>
  <tileset x="2" y="3">
    <tilex>0</tilex>
    <tiley>0</tiley>
    <perms>Open</perms>
  </tileset>
  <tileset x="3" y="3">
    <tilex>0</tilex>
    <tiley>0</tiley>
    <perms>Open</perms>
  </tileset>
  <tileset x="4" y="3">
    <tilex>0</tilex>
    <tiley>0</tiley>
    <perms>Open</perms>
  </tileset>
  <tileset x="5" y="3">
    <tilex>0</tilex>
    <tiley>0</tiley>
    <perms>Open</perms>
  </tileset>
  <tileset x="6" y="3">
    <tilex>0</tilex>
    <tiley>0</tiley>
    <perms>Open</perms>
  </tileset>
  <tileset x="7" y="3">
    <tilex>0</tilex>
    <tiley>0</tiley>
    <perms>Open</perms>
  </tileset>
  <tileset x="8" y="3">
    <tilex>0</tilex>
    <tiley>0</tiley>
    <perms>Open</perms>
  </tileset>
  <tileset x="9" y="3">
    <tilex>0</tilex>
    <tiley>0</tiley>
    <perms>Open</perms>
  </tileset>
  <tileset x="10" y="3">
    <tilex>0</tilex>
    <tiley>0</tiley>
    <perms>Open</perms>
  </tileset>
  <tileset x="11" y="3">
    <tilex>0</tilex>
    <tiley>0</tiley>
    <perms>Open</perms>
  </tileset>
  <tileset x="12" y="3">
    <tilex>0</tilex>
    <tiley>0</tiley>
    <perms>Open</perms>
  </tileset>
  <tileset x="13" y="3">
    <tilex>0</tilex>
    <tiley>0</tiley>
    <perms>Open</perms>
  </tileset>
  <tileset x="14" y="3">
    <tilex>0</tilex>
    <tiley>0</tiley>
    <perms>Open</perms>
  </tileset>
  <tileset x="15" y="3">
    <tilex>0</tilex>
    <tiley>0</tiley>
    <perms>Open</perms>
  </tileset>
  <tileset x="16" y="3">
    <tilex>0</tilex>
    <tiley>0</tiley>
    <perms>Open</perms>
  </tileset>
  <tileset x="17" y="3">
    <tilex>0</tilex>
    <tiley>0</tiley>
    <perms>Open</perms>
  </tileset>
  <tileset x="18" y="3">
    <tilex>0</tilex>
    <tiley>0</tiley>
    <perms>Open</perms>
  </tileset>
  <tileset x="19" y="3">
    <tilex>0</tilex>
    <tiley>0</tiley>
    <perms>Open</perms>
  </tileset>
  <tileset x="20" y="3">
    <tilex>0</tilex>
    <tiley>0</tiley>
    <perms>Open</perms>
  </tileset>
  <tileset x="21" y="3">
    <tilex>0</tilex>
    <tiley>0</tiley>
    <perms>Open</perms>
  </tileset>
  <tileset x="22" y="3">
    <tilex>0</tilex>
    <tiley>0</tiley>
    <perms>Open</perms>
  </tileset>
  <tileset x="23" y="3">
    <tilex>-1</tilex>
    <tiley>-1</tiley>
    <perms>Impassable</perms>
  </tileset>
  <tileset x="0" y="4">
    <tilex>-1</tilex>
    <tiley>-1</tiley>
    <perms>Impassable</perms>
  </tileset>
  <tileset x="1" y="4">
    <tilex>0</tilex>
    <tiley>0</tiley>
    <perms>Open</perms>
  </tileset>
  <tileset x="2" y="4">
    <tilex>8</tilex>
    <tiley>0</tiley>
    <perms>Open</perms>
  </tileset>
  <tileset x="3" y="4">
    <tilex>0</tilex>
    <tiley>0</tiley>
    <perms>Open</perms>
  </tileset>
  <tileset x="4" y="4">
    <tilex>0</tilex>
    <tiley>0</tiley>
    <perms>Open</perms>
  </tileset>
  <tileset x="5" y="4">
    <tilex>0</tilex>
    <tiley>0</tiley>
    <perms>Open</perms>
  </tileset>
  <tileset x="6" y="4">
    <tilex>0</tilex>
    <tiley>0</tiley>
    <perms>Open</perms>
  </tileset>
  <tileset x="7" y="4">
    <tilex>0</tilex>
    <tiley>0</tiley>
    <perms>Open</perms>
  </tileset>
  <tileset x="8" y="4">
    <tilex>0</tilex>
    <tiley>0</tiley>
    <perms>Open</perms>
  </tileset>
  <tileset x="9" y="4">
    <tilex>0</tilex>
    <tiley>0</tiley>
    <perms>Open</perms>
  </tileset>
  <tileset x="10" y="4">
    <tilex>0</tilex>
    <tiley>0</tiley>
    <perms>Open</perms>
  </tileset>
  <tileset x="11" y="4">
    <tilex>0</tilex>
    <tiley>0</tiley>
    <perms>Open</perms>
  </tileset>
  <tileset x="12" y="4">
    <tilex>0</tilex>
    <tiley>0</tiley>
    <perms>Open</perms>
  </tileset>
  <tileset x="13" y="4">
    <tilex>0</tilex>
    <tiley>0</tiley>
    <perms>Open</perms>
  </tileset>
  <tileset x="14" y="4">
    <tilex>0</tilex>
    <tiley>0</tiley>
    <perms>Open</perms>
  </tileset>
  <tileset x="15" y="4">
    <tilex>0</tilex>
    <tiley>0</tiley>
    <perms>Open</perms>
  </tileset>
  <tileset x="16" y="4">
    <tilex>0</tilex>
    <tiley>0</tiley>
    <perms>Open</perms>
  </tileset>
  <tileset x="17" y="4">
    <tilex>0</tilex>
    <tiley>0</tiley>
    <perms>Open</perms>
  </tileset>
  <tileset x="18" y="4">
    <tilex>0</tilex>
    <tiley>0</tiley>
    <perms>Open</perms>
  </tileset>
  <tileset x="19" y="4">
    <tilex>0</tilex>
    <tiley>0</tiley>
    <perms>Open</perms>
  </tileset>
  <tileset x="20" y="4">
    <tilex>0</tilex>
    <tiley>0</tiley>
    <perms>Open</perms>
  </tileset>
  <tileset x="21" y="4">
    <tilex>0</tilex>
    <tiley>0</tiley>
    <perms>Open</perms>
  </tileset>
  <tileset x="22" y="4">
    <tilex>0</tilex>
    <tiley>0</tiley>
    <perms>Open</perms>
  </tileset>
  <tileset x="23" y="4">
    <tilex>-1</tilex>
    <tiley>-1</tiley>
    <perms>Impassable</perms>
  </tileset>
  <tileset x="0" y="5">
    <tilex>-1</tilex>
    <tiley>-1</tiley>
    <perms>Impassable</perms>
  </tileset>
  <tileset x="1" y="5">
    <tilex>0</tilex>
    <tiley>0</tiley>
    <perms>Open</perms>
  </tileset>
  <tileset x="2" y="5">
    <tilex>0</tilex>
    <tiley>0</tiley>
    <perms>Open</perms>
  </tileset>
  <tileset x="3" y="5">
    <tilex>0</tilex>
    <tiley>0</tiley>
    <perms>Open</perms>
  </tileset>
  <tileset x="4" y="5">
    <tilex>0</tilex>
    <tiley>0</tiley>
    <perms>Open</perms>
  </tileset>
  <tileset x="5" y="5">
    <tilex>0</tilex>
    <tiley>0</tiley>
    <perms>Open</perms>
  </tileset>
  <tileset x="6" y="5">
    <tilex>0</tilex>
    <tiley>0</tiley>
    <perms>Open</perms>
  </tileset>
  <tileset x="7" y="5">
    <tilex>1</tilex>
    <tiley>0</tiley>
    <perms>Open</perms>
  </tileset>
  <tileset x="8" y="5">
    <tilex>0</tilex>
    <tiley>0</tiley>
    <perms>Open</perms>
  </tileset>
  <tileset x="9" y="5">
    <tilex>0</tilex>
    <tiley>0</tiley>
    <perms>Open</perms>
  </tileset>
  <tileset x="10" y="5">
    <tilex>0</tilex>
    <tiley>0</tiley>
    <perms>Open</perms>
  </tileset>
  <tileset x="11" y="5">
    <tilex>0</tilex>
    <tiley>0</tiley>
    <perms>Open</perms>
  </tileset>
  <tileset x="12" y="5">
    <tilex>0</tilex>
    <tiley>0</tiley>
    <perms>Open</perms>
  </tileset>
  <tileset x="13" y="5">
    <tilex>0</tilex>
    <tiley>0</tiley>
    <perms>Open</perms>
  </tileset>
  <tileset x="14" y="5">
    <tilex>0</tilex>
    <tiley>0</tiley>
    <perms>Open</perms>
  </tileset>
  <tileset x="15" y="5">
    <tilex>0</tilex>
    <tiley>0</tiley>
    <perms>Open</perms>
  </tileset>
  <tileset x="16" y="5">
    <tilex>0</tilex>
    <tiley>0</tiley>
    <perms>Open</perms>
  </tileset>
  <tileset x="17" y="5">
    <tilex>0</tilex>
    <tiley>0</tiley>
    <perms>Open</perms>
  </tileset>
  <tileset x="18" y="5">
    <tilex>0</tilex>
    <tiley>0</tiley>
    <perms>Open</perms>
  </tileset>
  <tileset x="19" y="5">
    <tilex>0</tilex>
    <tiley>0</tiley>
    <perms>Open</perms>
  </tileset>
  <tileset x="20" y="5">
    <tilex>0</tilex>
    <tiley>0</tiley>
    <perms>Open</perms>
  </tileset>
  <tileset x="21" y="5">
    <tilex>0</tilex>
    <tiley>0</tiley>
    <perms>Open</perms>
  </tileset>
  <tileset x="22" y="5">
    <tilex>0</tilex>
    <tiley>0</tiley>
    <perms>Open</perms>
  </tileset>
  <tileset x="23" y="5">
    <tilex>-1</tilex>
    <tiley>-1</tiley>
    <perms>Impassable</perms>
  </tileset>
  <tileset x="0" y="6">
    <tilex>-1</tilex>
    <tiley>-1</tiley>
    <perms>Impassable</perms>
  </tileset>
  <tileset x="1" y="6">
    <tilex>0</tilex>
    <tiley>0</tiley>
    <perms>Open</perms>
  </tileset>
  <tileset x="2" y="6">
    <tilex>0</tilex>
    <tiley>0</tiley>
    <perms>Open</perms>
  </tileset>
  <tileset x="3" y="6">
    <tilex>0</tilex>
    <tiley>0</tiley>
    <perms>Open</perms>
  </tileset>
  <tileset x="4" y="6">
    <tilex>0</tilex>
    <tiley>0</tiley>
    <perms>Open</perms>
  </tileset>
  <tileset x="5" y="6">
    <tilex>0</tilex>
    <tiley>0</tiley>
    <perms>Open</perms>
  </tileset>
  <tileset x="6" y="6">
    <tilex>0</tilex>
    <tiley>0</tiley>
    <perms>Open</perms>
  </tileset>
  <tileset x="7" y="6">
    <tilex>0</tilex>
    <tiley>0</tiley>
    <perms>Open</perms>
  </tileset>
  <tileset x="8" y="6">
    <tilex>0</tilex>
    <tiley>0</tiley>
    <perms>Open</perms>
  </tileset>
  <tileset x="9" y="6">
    <tilex>0</tilex>
    <tiley>0</tiley>
    <perms>Open</perms>
  </tileset>
  <tileset x="10" y="6">
    <tilex>0</tilex>
    <tiley>0</tiley>
    <perms>Open</perms>
  </tileset>
  <tileset x="11" y="6">
    <tilex>0</tilex>
    <tiley>0</tiley>
    <perms>Open</perms>
  </tileset>
  <tileset x="12" y="6">
    <tilex>0</tilex>
    <tiley>0</tiley>
    <perms>Open</perms>
  </tileset>
  <tileset x="13" y="6">
    <tilex>0</tilex>
    <tiley>0</tiley>
    <perms>Open</perms>
  </tileset>
  <tileset x="14" y="6">
    <tilex>0</tilex>
    <tiley>0</tiley>
    <perms>Open</perms>
  </tileset>
  <tileset x="15" y="6">
    <tilex>0</tilex>
    <tiley>0</tiley>
    <perms>Open</perms>
  </tileset>
  <tileset x="16" y="6">
    <tilex>0</tilex>
    <tiley>0</tiley>
    <perms>Open</perms>
  </tileset>
  <tileset x="17" y="6">
    <tilex>0</tilex>
    <tiley>0</tiley>
    <perms>Open</perms>
  </tileset>
  <tileset x="18" y="6">
    <tilex>0</tilex>
    <tiley>0</tiley>
    <perms>Open</perms>
  </tileset>
  <tileset x="19" y="6">
    <tilex>0</tilex>
    <tiley>0</tiley>
    <perms>Open</perms>
  </tileset>
  <tileset x="20" y="6">
    <tilex>0</tilex>
    <tiley>0</tiley>
    <perms>Open</perms>
  </tileset>
  <tileset x="21" y="6">
    <tilex>0</tilex>
    <tiley>0</tiley>
    <perms>Open</perms>
  </tileset>
  <tileset x="22" y="6">
    <tilex>0</tilex>
    <tiley>0</tiley>
    <perms>Open</perms>
  </tileset>
  <tileset x="23" y="6">
    <tilex>-1</tilex>
    <tiley>-1</tiley>
    <perms>Impassable</perms>
  </tileset>
  <tileset x="0" y="7">
    <tilex>-1</tilex>
    <tiley>-1</tiley>
    <perms>Impassable</perms>
  </tileset>
  <tileset x="1" y="7">
    <tilex>0</tilex>
    <tiley>0</tiley>
    <perms>Open</perms>
  </tileset>
  <tileset x="2" y="7">
    <tilex>0</tilex>
    <tiley>0</tiley>
    <perms>Open</perms>
  </tileset>
  <tileset x="3" y="7">
    <tilex>0</tilex>
    <tiley>0</tiley>
    <perms>Open</perms>
  </tileset>
  <tileset x="4" y="7">
    <tilex>0</tilex>
    <tiley>0</tiley>
    <perms>Open</perms>
  </tileset>
  <tileset x="5" y="7">
    <tilex>0</tilex>
    <tiley>0</tiley>
    <perms>Open</perms>
  </tileset>
  <tileset x="6" y="7">
    <tilex>0</tilex>
    <tiley>0</tiley>
    <perms>Open</perms>
  </tileset>
  <tileset x="7" y="7">
    <tilex>0</tilex>
    <tiley>0</tiley>
    <perms>Open</perms>
  </tileset>
  <tileset x="8" y="7">
    <tilex>0</tilex>
    <tiley>0</tiley>
    <perms>Open</perms>
  </tileset>
  <tileset x="9" y="7">
    <tilex>0</tilex>
    <tiley>0</tiley>
    <perms>Open</perms>
  </tileset>
  <tileset x="10" y="7">
    <tilex>0</tilex>
    <tiley>0</tiley>
    <perms>Open</perms>
  </tileset>
  <tileset x="11" y="7">
    <tilex>0</tilex>
    <tiley>0</tiley>
    <perms>Open</perms>
  </tileset>
  <tileset x="12" y="7">
    <tilex>0</tilex>
    <tiley>0</tiley>
    <perms>Open</perms>
  </tileset>
  <tileset x="13" y="7">
    <tilex>0</tilex>
    <tiley>0</tiley>
    <perms>Open</perms>
  </tileset>
  <tileset x="14" y="7">
    <tilex>0</tilex>
    <tiley>0</tiley>
    <perms>Open</perms>
  </tileset>
  <tileset x="15" y="7">
    <tilex>0</tilex>
    <tiley>0</tiley>
    <perms>Open</perms>
  </tileset>
  <tileset x="16" y="7">
    <tilex>0</tilex>
    <tiley>0</tiley>
    <perms>Open</perms>
  </tileset>
  <tileset x="17" y="7">
    <tilex>0</tilex>
    <tiley>0</tiley>
    <perms>Open</perms>
  </tileset>
  <tileset x="18" y="7">
    <tilex>0</tilex>
    <tiley>0</tiley>
    <perms>Open</perms>
  </tileset>
  <tileset x="19" y="7">
    <tilex>0</tilex>
    <tiley>0</tiley>
    <perms>Open</perms>
  </tileset>
  <tileset x="20" y="7">
    <tilex>0</tilex>
    <tiley>0</tiley>
    <perms>Open</perms>
  </tileset>
  <tileset x="21" y="7">
    <tilex>0</tilex>
    <tiley>0</tiley>
    <perms>Open</perms>
  </tileset>
  <tileset x="22" y="7">
    <tilex>0</tilex>
    <tiley>0</tiley>
    <perms>Open</perms>
  </tileset>
  <tileset x="23" y="7">
    <tilex>-1</tilex>
    <tiley>-1</tiley>
    <perms>Impassable</perms>
  </tileset>
  <tileset x="0" y="8">
    <tilex>-1</tilex>
    <tiley>-1</tiley>
    <perms>Impassable</perms>
  </tileset>
  <tileset x="1" y="8">
    <tilex>0</tilex>
    <tiley>0</tiley>
    <perms>Open</perms>
  </tileset>
  <tileset x="2" y="8">
    <tilex>0</tilex>
    <tiley>0</tiley>
    <perms>Open</perms>
  </tileset>
  <tileset x="3" y="8">
    <tilex>0</tilex>
    <tiley>0</tiley>
    <perms>Open</perms>
  </tileset>
  <tileset x="4" y="8">
    <tilex>0</tilex>
    <tiley>0</tiley>
    <perms>Open</perms>
  </tileset>
  <tileset x="5" y="8">
    <tilex>0</tilex>
    <tiley>0</tiley>
    <perms>Open</perms>
  </tileset>
  <tileset x="6" y="8">
    <tilex>0</tilex>
    <tiley>0</tiley>
    <perms>Open</perms>
  </tileset>
  <tileset x="7" y="8">
    <tilex>0</tilex>
    <tiley>0</tiley>
    <perms>Open</perms>
  </tileset>
  <tileset x="8" y="8">
    <tilex>0</tilex>
    <tiley>0</tiley>
    <perms>Open</perms>
  </tileset>
  <tileset x="9" y="8">
    <tilex>0</tilex>
    <tiley>0</tiley>
    <perms>Open</perms>
  </tileset>
  <tileset x="10" y="8">
    <tilex>0</tilex>
    <tiley>0</tiley>
    <perms>Open</perms>
  </tileset>
  <tileset x="11" y="8">
    <tilex>0</tilex>
    <tiley>0</tiley>
    <perms>Open</perms>
  </tileset>
  <tileset x="12" y="8">
    <tilex>0</tilex>
    <tiley>0</tiley>
    <perms>Open</perms>
  </tileset>
  <tileset x="13" y="8">
    <tilex>0</tilex>
    <tiley>0</tiley>
    <perms>Open</perms>
  </tileset>
  <tileset x="14" y="8">
    <tilex>0</tilex>
    <tiley>0</tiley>
    <perms>Open</perms>
  </tileset>
  <tileset x="15" y="8">
    <tilex>0</tilex>
    <tiley>0</tiley>
    <perms>Open</perms>
  </tileset>
  <tileset x="16" y="8">
    <tilex>0</tilex>
    <tiley>0</tiley>
    <perms>Open</perms>
  </tileset>
  <tileset x="17" y="8">
    <tilex>0</tilex>
    <tiley>0</tiley>
    <perms>Open</perms>
  </tileset>
  <tileset x="18" y="8">
    <tilex>0</tilex>
    <tiley>0</tiley>
    <perms>Open</perms>
  </tileset>
  <tileset x="19" y="8">
    <tilex>0</tilex>
    <tiley>0</tiley>
    <perms>Open</perms>
  </tileset>
  <tileset x="20" y="8">
    <tilex>8</tilex>
    <tiley>0</tiley>
    <perms>Open</perms>
  </tileset>
  <tileset x="21" y="8">
    <tilex>0</tilex>
    <tiley>0</tiley>
    <perms>Open</perms>
  </tileset>
  <tileset x="22" y="8">
    <tilex>0</tilex>
    <tiley>0</tiley>
    <perms>Open</perms>
  </tileset>
  <tileset x="23" y="8">
    <tilex>-1</tilex>
    <tiley>-1</tiley>
    <perms>Open</perms>
  </tileset>
  <tileset x="0" y="9">
    <tilex>-1</tilex>
    <tiley>-1</tiley>
    <perms>Impassable</perms>
  </tileset>
  <tileset x="1" y="9">
    <tilex>0</tilex>
    <tiley>0</tiley>
    <perms>Open</perms>
  </tileset>
  <tileset x="2" y="9">
    <tilex>0</tilex>
    <tiley>0</tiley>
    <perms>Open</perms>
  </tileset>
  <tileset x="3" y="9">
    <tilex>1</tilex>
    <tiley>0</tiley>
    <perms>Open</perms>
  </tileset>
  <tileset x="4" y="9">
    <tilex>0</tilex>
    <tiley>0</tiley>
    <perms>Open</perms>
  </tileset>
  <tileset x="5" y="9">
    <tilex>0</tilex>
    <tiley>0</tiley>
    <perms>Open</perms>
  </tileset>
  <tileset x="6" y="9">
    <tilex>0</tilex>
    <tiley>0</tiley>
    <perms>Open</perms>
  </tileset>
  <tileset x="7" y="9">
    <tilex>0</tilex>
    <tiley>0</tiley>
    <perms>Open</perms>
  </tileset>
  <tileset x="8" y="9">
    <tilex>0</tilex>
    <tiley>0</tiley>
    <perms>Open</perms>
  </tileset>
  <tileset x="9" y="9">
    <tilex>0</tilex>
    <tiley>0</tiley>
    <perms>Open</perms>
  </tileset>
  <tileset x="10" y="9">
    <tilex>0</tilex>
    <tiley>0</tiley>
    <perms>Open</perms>
  </tileset>
  <tileset x="11" y="9">
    <tilex>0</tilex>
    <tiley>0</tiley>
    <perms>Open</perms>
  </tileset>
  <tileset x="12" y="9">
    <tilex>0</tilex>
    <tiley>0</tiley>
    <perms>Open</perms>
  </tileset>
  <tileset x="13" y="9">
    <tilex>0</tilex>
    <tiley>0</tiley>
    <perms>Open</perms>
  </tileset>
  <tileset x="14" y="9">
    <tilex>0</tilex>
    <tiley>0</tiley>
    <perms>Open</perms>
  </tileset>
  <tileset x="15" y="9">
    <tilex>0</tilex>
    <tiley>0</tiley>
    <perms>Open</perms>
  </tileset>
  <tileset x="16" y="9">
    <tilex>0</tilex>
    <tiley>0</tiley>
    <perms>Open</perms>
  </tileset>
  <tileset x="17" y="9">
    <tilex>0</tilex>
    <tiley>0</tiley>
    <perms>Open</perms>
  </tileset>
  <tileset x="18" y="9">
    <tilex>0</tilex>
    <tiley>0</tiley>
    <perms>Open</perms>
  </tileset>
  <tileset x="19" y="9">
    <tilex>0</tilex>
    <tiley>0</tiley>
    <perms>Open</perms>
  </tileset>
  <tileset x="20" y="9">
    <tilex>0</tilex>
    <tiley>0</tiley>
    <perms>Open</perms>
  </tileset>
  <tileset x="21" y="9">
    <tilex>0</tilex>
    <tiley>0</tiley>
    <perms>Open</perms>
  </tileset>
  <tileset x="22" y="9">
    <tilex>0</tilex>
    <tiley>0</tiley>
    <perms>Open</perms>
  </tileset>
  <tileset x="23" y="9">
    <tilex>-1</tilex>
    <tiley>-1</tiley>
    <perms>Impassable</perms>
  </tileset>
</map>